{
  "name": "patchouli.seasonsextras.crops",
  "category": "seasonsextras:compendium",
  "icon": "minecraft:wheat",
  "pages": [
    {
      "type": "patchouli:text",
      "title": "patchouli.seasonsextras.crops",
      "text": "patchouli.seasonsextras.crops_text"
    },
    {
      "type": "seasonsextras:crop_search",
      "title": "patchouli.seasonsextras.entries"
    },
    {
      "type": "seasonsextras:modifiable",
      "modify": "seasonsextras:seasonal_crops"
    }
  ],
  "read_by_default": true,
  "sortnum": 1
}